ooli/__init__.py
ooli/ooli.py
ooli-1.1.3.dist-info/METADATA
ooli-1.1.3.dist-info/WHEEL
ooli-1.1.3.dist-info/entry_points.txt
ooli-1.1.3.dist-info/top_level.txt
ooli-1.1.3.dist-info/RECORD
