Metadata-Version: 2.1
Name: ooli
Version: 1.1.3
Summary: A tool for scanning APK Smali files for keywords.
Author: Jina
Requires-Python: >=3.6
